{
    "fluentMethods": true,
    "relationships": [
        {
            "relationshipName": "company",
            "otherEntityName": "company",
            "relationshipType": "many-to-one",
            "otherEntityField": "id"
        }
    ],
    "fields": [
        {
            "fieldName": "name",
            "fieldType": "String"
        },
        {
            "fieldName": "description",
            "fieldType": "String"
        },
        {
            "fieldName": "fileUrl",
            "fieldType": "String"
        },
        {
            "fieldName": "fileName",
            "fieldType": "String"
        },
        {
            "fieldName": "uploadDate",
            "fieldType": "ZonedDateTime"
        },
        {
            "fieldName": "deleted",
            "fieldType": "Integer"
        },
        {
            "fieldName": "status",
            "fieldType": "Integer"
        }
    ],
    "changelogDate": "20200131175316",
    "dto": "mapstruct",
    "service": "serviceClass",
    "entityTableName": "condominium_record",
    "jpaMetamodelFiltering": false,
    "pagination": "infinite-scroll"
}
