{
    "fluentMethods": true,
    "relationships": [
        {
            "relationshipName": "subsidiaryType",
            "otherEntityName": "subsidiaryType",
            "relationshipType": "many-to-one",
            "otherEntityField": "id"
        },
        {
            "relationshipName": "house",
            "otherEntityName": "house",
            "relationshipType": "many-to-one",
            "otherEntityField": "id"
        }
    ],
    "fields": [
        {
            "fieldName": "name",
            "fieldType": "String",
            "fieldValidateRules": [
                "required"
            ]
        },
        {
            "fieldName": "deleted",
            "fieldType": "Integer"
        },
        {
            "fieldName": "description",
            "fieldType": "String"
        }
    ],
    "changelogDate": "20191128050641",
    "dto": "mapstruct",
    "service": "serviceClass",
    "entityTableName": "subsidiary",
    "jpaMetamodelFiltering": false,
    "pagination": "infinite-scroll"
}
